{
    "1016960892421812284": {
        "tag": "\u1d36\u1d37",
        "support": "https://discord.gg/mHWxvWtx"
    },
    "973836719587733514": {
        "tag": "\u2d3d\u039b\u3006",
        "stag": "\u1d3f\u1d2c",
        "link": "https://discord.gg/raop",
        "vanity": "https://discord.gg/raop",
        "<@961927345038573619>": "<a:crownshine:1048999904678256642>  \ud835\udc6f\ud835\udc96\ud835\udc8f\ud835\udc95\ud835\udc86\ud835\udc93 \ud835\udc6b\ud835\udc82\ud835\udc6b\ud835\udc6b\ud835\udc9a.  <a:rc_bluecrown:1033803552935645366>",
        "<@713246713086869576>": "```Don't Ping Him, He Is Busy With Your Mom``` <:hacker_se_pareshan:1047122800869113926>",
        "<@1028362529006698576>": "<a:anshit_macchi:1052244018920165467> SaHiL DaDDy <a:anshit_macchi:1052244018920165467>"
    },
    "1041239115653451776": {
        "hii": "okk",
        "hi": "ok",
        "hiS": "okk",
        "hai": "ok",
        "hxi": "ok",
        "hzi": "ok",
        "hiss": "ok",
        "hizzz": "ok",
        "hzzi": "ok",
        "zxhi": "ok",
        "haazzjsi": "ok",
        "ssshi": "ok"
    },
    "1046306042398642246": {
        "i": "Bala!\n\nBala Bala Bala Bala\nBala Bala Bala Bala Baala\u2026\n\nBala Bala Shaitan Ka Saala\nBala Bala Ravan Ne Hai Paala\nBala Bala Shaitan Ka Sala\nBala Bala Ravan Ne Hai Paala\n\nSab Kahein Mujhe Shaitaan Ka Saala\nBala Bala Bala Bala\nLooto Looto Luto Luto Japta Hu Maala\n\nBala Bala Bala Bala\nSab Kahein Mujhe Shaitan Ka Saala\nBala Bala Bala Bala\nLog Bolein Baala Kya Cheez Hai Saala\nBala Bala Bala Bala\n\nLog Bolein Bala Kya Cheez Hai Saala\nRavan Ne Hai Paala Bole Beti, Mausi, Khala\nGore Se Gore Ka Munh Karta Hu Kaala\nKhud Ki Deewali Aur Auron Ka Deewala\n\nBala Bala Bala Chhichhori Pathshala\nBala Bala Bala Keeda of The Nala\n\nBala Bala Thats Right\n\nBala Bala Bala Bala\nBala Bala Bala Bala Baala\u2026\n\nKhata Hu Murga Daal Ke Masala\nGaribon Ke Munh Se Main Chheenu Main Niwala\nBala Bala Bala Bala Peg Patiyala\nBala Bala Bala Keeda of The Nala\n\nBala Bala\u2026.\n\nBala Bala Shaitan Ka Sala\nBala Bala Chhichhori Pathshala\nBala Bala Shaitan Ka Sala\nBala Bala Arre Ravan Ne Hai Paala\n\nBala Bala Shaitan Ka Sala\nBala Bala Chhichhori Pathshala\nBala Bala Shaitan Ka Sala\nBala Bala Arre Ravan Ne Hai Paala\n\nBala Bala Bala Bala\u2026"
    },
    "1046305209502138398": {
        "i": "Bala!\n\nBala Bala Bala Bala\nBala Bala Bala Bala Baala\u2026\n\nBala Bala Shaitan Ka Saala\nBala Bala Ravan Ne Hai Paala\nBala Bala Shaitan Ka Sala\nBala Bala Ravan Ne Hai Paala\n\nSab Kahein Mujhe Shaitaan Ka Saala\nBala Bala Bala Bala\nLooto Looto Luto Luto Japta Hu Maala\n\nBala Bala Bala Bala\nSab Kahein Mujhe Shaitan Ka Saala\nBala Bala Bala Bala\nLog Bolein Baala Kya Cheez Hai Saala\nBala Bala Bala Bala\n\nLog Bolein Bala Kya Cheez Hai Saala\nRavan Ne Hai Paala Bole Beti, Mausi, Khala\nGore Se Gore Ka Munh Karta Hu Kaala\nKhud Ki Deewali Aur Auron Ka Deewala\n\nBala Bala Bala Chhichhori Pathshala\nBala Bala Bala Keeda of The Nala\n\nBala Bala Thats Right\n\nBala Bala Bala Bala\nBala Bala Bala Bala Baala\u2026\n\nKhata Hu Murga Daal Ke Masala\nGaribon Ke Munh Se Main Chheenu Main Niwala\nBala Bala Bala Bala Peg Patiyala\nBala Bala Bala Keeda of The Nala\n\nBala Bala\u2026.\n\nBala Bala Shaitan Ka Sala\nBala Bala Chhichhori Pathshala\nBala Bala Shaitan Ka Sala\nBala Bala Arre Ravan Ne Hai Paala\n\nBala Bala Shaitan Ka Sala\nBala Bala Chhichhori Pathshala\nBala Bala Shaitan Ka Sala\nBala Bala Arre Ravan Ne Hai Paala\n\nBala Bala Bala Bala\u2026"
    },
    "1022506232227057775": {
        "tag": "<:TeddyFlowers:1038807422623567882>  `! \u03b6\u035c\u0361\ud835\udc0c\ud835\udc02\u3022`\n\n***Tag lagao Cool bano!!*** <:TeddyHeart:1038806833017663508>"
    },
    "939809060579061760": {},
    "950635426757107763": {
        "vanity": "https://discord.gg/feelhell",
        "tag": "\u219d",
        "link": "https://discord.gg/feelhell"
    },
    "1000735512891502632": {
        "vanity": "https://discord.gg/terms"
    },
    "991963593727803403": {},
    "1050118567024144405": {
        "vanity": "Add .gg/hrcx on your status/about me"
    },
    "996137339715866635": {
        "Robux": "If you got dm from apolex that you won Robux or anything so don't believe coz there is also a bot with apolex name."
    },
    "1019529276896329778": {
        "tag": "H\u2d3d\u3006",
        "<@961927345038573619>": "<a:crownshine:1048999904678256642> \u04c7\u01b2\u019d\u01ac\u0404\u01a6 \ud835\udc09\ud835\udc08\ud835\udc09\ud835\udc00 <a:crown_red:1043406323309625386> <:crown:1048043305591656529>",
        "<@1028362529006698576>": "<a:king_bb:1053323365454196796> **SaHiL DaDDy** <a:king_bb:1053323365454196796>",
        "<@910829375325343784>": "<a:king_bb:1053323365454196796> \ud835\udc80\ud835\udcfe\ud835\udd03\ud835\udcf2 DaDDy <a:king_bb:1053323365454196796>",
        "stag": "\u30e3\u1d34\u1d3f"
    },
    "1052431155808452719": {
        "Arpan": "ArPaN on ToP BiTcH < $ ``\u2764\ufe0f``"
    },
    "881174167922278452": {
        "<:accepted:1054000930703560817>": "<:sleepy:1054000807512641607>"
    }
}